jupymcp/__init__.py
jupymcp/__main__.py
jupymcp/main.py
jupymcp/model.py
jupymcp-0.3.0.dist-info/WHEEL
jupymcp-0.3.0.dist-info/entry_points.txt
jupymcp-0.3.0.dist-info/METADATA
jupymcp-0.3.0.dist-info/RECORD
