Metadata-Version: 2.3
Name: jupymcp
Version: 0.3.0
Summary: Jupyter + MCP with comprehensive resource support
Author: Ziya Tang (唐梓涯)
Author-email: Ziya Tang (唐梓涯) <tcztzy@gmail.com>
Classifier: Framework :: Jupyter
Classifier: Programming Language :: Python :: 3
Classifier: Programming Language :: Python :: 3 :: Only
Classifier: Programming Language :: Python :: 3.11
Classifier: Programming Language :: Python :: Implementation :: CPython
Classifier: Programming Language :: Python :: Implementation :: GraalPy
Classifier: Programming Language :: Python :: Implementation :: PyPy
Classifier: Topic :: Scientific/Engineering :: Artificial Intelligence
Classifier: Topic :: Scientific/Engineering :: Interface Engine/Protocol Translator
Classifier: Typing :: Typed
Requires-Dist: jupyter-client>=8.7.0
Requires-Dist: jupytext>=1.18.1
Requires-Dist: mcp>=1.25.0
Requires-Python: >=3.11
